internetarchiveocr/__init__.py
internetarchiveocr/language.py
internetarchiveocr/version.py
archive_ocr_tools-1.0.0.dist-info/METADATA
archive_ocr_tools-1.0.0.dist-info/WHEEL
archive_ocr_tools-1.0.0.dist-info/top_level.txt
archive_ocr_tools-1.0.0.dist-info/RECORD
