Metadata-Version: 2.1
Name: archive-ocr-tools
Version: 1.0.0
Summary: OCR utilities
Home-page: https://github.com/internetarchive/archive-ocr-tools
Download-URL: https://github.com/internetarchive/archive-ocr-tools/archive/1.0.0.tar.gz
Author: Merlijn Boris Wolf Wajer
Author-email: merlijn@archive.org
License: AGPL-3.0
Keywords: OCR,Internet Archive
Platform: UNKNOWN
Classifier: Development Status :: 3 - Alpha
Classifier: Intended Audience :: Developers
Classifier: License :: OSI Approved :: GNU Affero General Public License v3
Classifier: Programming Language :: Python :: 3
Requires-Python: >=3.6
Requires-Dist: iso-639 (==0.4.5)
